trame/__init__.py
trame/modules/__init__.py
trame/modules/router.py
trame/ui/__init__.py
trame/ui/router.py
trame/widgets/__init__.py
trame/widgets/router.py
trame_router/LICENSE
trame_router/__init__.py
trame_router/module/__init__.py
trame_router/module/vue2.py
trame_router/module/vue3.py
trame_router/module/vue2/trame-router.umd.min.js
trame_router/module/vue3/trame-router.umd.js
trame_router/ui/__init__.py
trame_router/ui/router.py
trame_router/widgets/__init__.py
trame_router/widgets/router.py
trame_router-2.3.0.dist-info/LICENSE
trame_router-2.3.0.dist-info/METADATA
trame_router-2.3.0.dist-info/WHEEL
trame_router-2.3.0.dist-info/top_level.txt
trame_router-2.3.0.dist-info/RECORD
